{
  "verb_rank": 26,
  "verb_english": "leave",
  "verb_russian": "покидать",
  "verb_infinitive": "ayrılmak",
  "turkish_verb": {
    "verb_full": "ayrılacaktık",
    "root": "ayrıl",
    "tense_affix": "acaktı",
    "verb_tense": "geçmiş_gelecek_zaman",
    "personal_pronoun": "biz",
    "personal_affix": "k",
    "polarity": "positive",
    "negative_affix": null
  },
  "english_example_sentence": "We were going to leave this small town with my friend.",
  "russian_example_sentence": "Мы собирались уехать из этого маленького городка с моим другом.",
  "turkish_example_sentence": "Biz, bu küçük kasabadan arkadaşımla ayrılacaktık.",
  "turkish_example_sentence_with_blank": "Biz, bu küçük kasabadan arkadaşımla ______."
}