{
  "verb_rank": 26,
  "verb_english": "leave",
  "verb_russian": "покидать",
  "verb_infinitive": "ayrılmak",
  "turkish_verb": {
    "verb_full": "ayrılmıyoruz",
    "root": "ayrıl",
    "tense_affix": "yor",
    "verb_tense": "şimdiki_zaman",
    "personal_pronoun": "biz",
    "personal_affix": "uz",
    "polarity": "negative",
    "negative_affix": "mı"
  },
  "english_example_sentence": "We are not leaving this beautiful city with our friends.",
  "russian_example_sentence": "Мы не покидаем этот красивый город с нашими друзьями.",
  "turkish_example_sentence": "Biz bu güzel şehirden arkadaşlarımızla ayrılmıyoruz.",
  "turkish_example_sentence_with_blank": "Biz bu güzel şehirden arkadaşlarımızla ______."
}