{
  "verb_rank": 26,
  "verb_english": "leave",
  "verb_russian": "покидать",
  "verb_infinitive": "ayrılmak",
  "turkish_verb": {
    "verb_full": "ayrılarak",
    "root": "ayrıl",
    "tense_affix": "arak",
    "verb_tense": "zarf_fiil",
    "personal_pronoun": null,
    "personal_affix": "",
    "polarity": "positive",
    "negative_affix": null
  },
  "english_example_sentence": "The young man started a new life by leaving his beautiful old house.",
  "russian_example_sentence": "Молодой человек начал новую жизнь, покинув свой старый красивый дом.",
  "turkish_example_sentence": "Genç adam, eski güzel evinden ayrılarak yeni bir hayata başladı.",
  "turkish_example_sentence_with_blank": "Genç adam, eski güzel evinden ______ yeni bir hayata başladı."
}