{
  "verb_rank": 65,
  "verb_english": "to add",
  "verb_russian": "добавлять",
  "verb_infinitive": "eklemek",
  "turkish_verb": {
    "verb_full": "ekledik",
    "root": "ekle",
    "tense_affix": "di",
    "verb_tense": "geçmiş_zaman",
    "personal_pronoun": "biz",
    "personal_affix": "k",
    "polarity": "positive",
    "negative_affix": null
  },
  "english_example_sentence": "We added new features to the project.",
  "russian_example_sentence": "Мы добавили новые функции в проект.",
  "turkish_example_sentence": "Biz projeye yeni özellikler ekledik.",
  "turkish_example_sentence_with_blank": "Biz projeye yeni özellikler ______."
}