{
  "verb_rank": 16,
  "verb_english": "find",
  "verb_russian": "находить",
  "verb_infinitive": "bulmak",
  "turkish_verb": {
    "verb_full": "bulmuyorsunuz",
    "root": "bul",
    "tense_affix": "yor",
    "verb_tense": "şimdiki_zaman",
    "personal_pronoun": "siz",
    "personal_affix": "sunuz",
    "polarity": "negative",
    "negative_affix": "mu"
  },
  "english_example_sentence": "You are not finding the old key in the big bag.",
  "russian_example_sentence": "Вы не находите старый ключ в большой сумке.",
  "turkish_example_sentence": "Siz büyük çantada eski anahtarı bulmuyorsunuz.",
  "turkish_example_sentence_with_blank": "Siz büyük çantada eski anahtarı ______."
}