{
  "verb_rank": 89,
  "verb_english": "to suggest",
  "verb_russian": "предлагать",
  "verb_infinitive": "önermek",
  "turkish_verb": {
    "verb_full": "öneresiniz",
    "root": "öner",
    "tense_affix": "e",
    "verb_tense": "istek_kipi",
    "personal_pronoun": "siz",
    "personal_affix": "siniz",
    "polarity": "positive",
    "negative_affix": null
  },
  "english_example_sentence": "You should suggest a new idea in this important meeting.",
  "russian_example_sentence": "Вам следует предложить новую идею на этом важном собрании.",
  "turkish_example_sentence": "Siz bu önemli toplantıda yeni bir fikir öneresiniz.",
  "turkish_example_sentence_with_blank": "Siz bu önemli toplantıda yeni bir fikir ______."
}