{
  "verb_rank": 45,
  "verb_english": "to provide",
  "verb_russian": "предоставлять",
  "verb_infinitive": "sağlamak",
  "turkish_verb": {
    "verb_full": "sağlamayacak",
    "root": "sağla",
    "tense_affix": "yacak",
    "verb_tense": "gelecek_zaman",
    "personal_pronoun": "o",
    "personal_affix": "",
    "polarity": "negative",
    "negative_affix": "ma"
  },
  "english_example_sentence": "The little child will not provide support to his mother on this matter.",
  "russian_example_sentence": "Маленький ребенок не окажет поддержку своей матери в этом вопросе.",
  "turkish_example_sentence": "Küçük çocuk, annesine bu konuda destek sağlamayacak.",
  "turkish_example_sentence_with_blank": "Küçük çocuk, annesine bu konuda destek ______."
}