{
  "verb_rank": 71,
  "verb_english": "offer",
  "verb_russian": "предлагать",
  "verb_infinitive": "teklif etmek",
  "turkish_verb": {
    "verb_full": "teklif etmiş olsalar",
    "root": "teklif et",
    "tense_affix": "miş olsa",
    "verb_tense": "farzî_geçmiş_zaman",
    "personal_pronoun": "onlar",
    "personal_affix": "lar",
    "polarity": "positive",
    "negative_affix": null
  },
  "english_example_sentence": "If the company officials had offered a better project, they would have gotten the job.",
  "russian_example_sentence": "Если бы представители компании предложили лучший проект, они бы получили работу.",
  "turkish_example_sentence": "Eğer şirket yetkilileri daha iyi bir proje teklif etmiş olsalar, işi alırlardı.",
  "turkish_example_sentence_with_blank": "Eğer şirket yetkilileri daha iyi bir proje ______, işi alırlardı."
}