{
  "verb_rank": 31,
  "verb_english": "begin",
  "verb_russian": "начинать",
  "verb_infinitive": "başlamak",
  "turkish_verb": {
    "verb_full": "başlamayacaksınız",
    "root": "başla",
    "tense_affix": "yacak",
    "verb_tense": "gelecek_zaman",
    "personal_pronoun": "siz",
    "personal_affix": "sınız",
    "polarity": "negative",
    "negative_affix": "ma"
  },
  "english_example_sentence": "You will not begin the risky business venture",
  "russian_example_sentence": "Вы не начнёте рискованный деловой проект",
  "turkish_example_sentence": "Siz riskli iş girişimini başlamayacaksınız",
  "turkish_example_sentence_with_blank": "Siz riskli iş girişimini ______"
}