{
  "verb_rank": 76,
  "verb_english": "buy",
  "verb_russian": "покупать",
  "verb_infinitive": "satın almak",
  "turkish_verb": {
    "verb_full": "satın almayacaksınız",
    "root": "satın al",
    "tense_affix": "acak",
    "verb_tense": "gelecek_zaman",
    "personal_pronoun": "siz",
    "personal_affix": "sınız",
    "polarity": "negative",
    "negative_affix": "ma"
  },
  "english_example_sentence": "You will not buy those counterfeit fake watches",
  "russian_example_sentence": "Вы не купите те поддельные часы",
  "turkish_example_sentence": "Siz sahte markasız saatleri satın almayacaksınız",
  "turkish_example_sentence_with_blank": "Siz sahte markasız saatleri ______"
}