{
  "verb_rank": 80,
  "verb_english": "to send",
  "verb_russian": "отправлять",
  "verb_infinitive": "göndermek",
  "turkish_verb": {
    "verb_full": "gönderirsiniz",
    "root": "gönder",
    "tense_affix": "ir",
    "verb_tense": "geniş_zaman",
    "personal_pronoun": "siz",
    "personal_affix": "siniz",
    "polarity": "positive",
    "negative_affix": null
  },
  "english_example_sentence": "Every year you send us beautiful gifts.",
  "russian_example_sentence": "Каждый год вы отправляете нам красивые подарки.",
  "turkish_example_sentence": "Her yıl bize güzel hediyeler gönderirsiniz.",
  "turkish_example_sentence_with_blank": "Her yıl bize güzel hediyeler ______."
}