{
  "verb_rank": 35,
  "verb_english": "hear",
  "verb_russian": "слышать",
  "verb_infinitive": "duymak",
  "turkish_verb": {
    "verb_full": "duymadınız",
    "root": "duy",
    "tense_affix": "dı",
    "verb_tense": "geçmiş_zaman",
    "personal_pronoun": "siz",
    "personal_affix": "nız",
    "polarity": "negative",
    "negative_affix": "ma"
  },
  "english_example_sentence": "You didn't hear the teacher's important words.",
  "russian_example_sentence": "Вы не слышали важные слова учителя.",
  "turkish_example_sentence": "Siz öğretmenin önemli sözlerini duymadınız.",
  "turkish_example_sentence_with_blank": "Siz öğretmenin önemli sözlerini ______."
}