{
  "verb_rank": 84,
  "verb_english": "to fall",
  "verb_russian": "падать",
  "verb_infinitive": "düşmek",
  "turkish_verb": {
    "verb_full": "düşerim",
    "root": "düş",
    "tense_affix": "er",
    "verb_tense": "geniş_zaman",
    "personal_pronoun": "ben",
    "personal_affix": "im",
    "polarity": "positive",
    "negative_affix": null
  },
  "english_example_sentence": "I always fall from a tall ladder.",
  "russian_example_sentence": "Я всегда падаю с высокой лестницы.",
  "turkish_example_sentence": "Her zaman uzun bir merdivenden düşerim.",
  "turkish_example_sentence_with_blank": "Her zaman uzun bir merdivenden ______."
}