{
  "verb_rank": 84,
  "verb_english": "fall",
  "verb_russian": "падать",
  "verb_infinitive": "düşmek",
  "turkish_verb": {
    "verb_full": "düşmeyecek",
    "root": "düş",
    "tense_affix": "ecek",
    "verb_tense": "gelecek_zaman",
    "personal_pronoun": "o",
    "personal_affix": null,
    "polarity": "negative",
    "negative_affix": "me"
  },
  "english_example_sentence": "The heavy snow will not fall on the warm spring day",
  "russian_example_sentence": "Тяжелый снег не упадет в теплый весенний день",
  "turkish_example_sentence": "Ağır kar sıcak bahar gününde düşmeyecek",
  "turkish_example_sentence_with_blank": "Ağır kar sıcak bahar gününde ______"
}