{
  "verb_rank": 23,
  "verb_english": "need",
  "verb_russian": "нуждаться",
  "verb_infinitive": "ihtiyaç duymak",
  "turkish_verb": {
    "verb_full": "ihtiyaç duyasın",
    "root": "ihtiyaç duy",
    "tense_affix": "asın",
    "verb_tense": "istek_kipi",
    "personal_pronoun": "sen",
    "personal_affix": "sın",
    "polarity": "positive",
    "negative_affix": null
  },
  "english_example_sentence": "May you need our help.",
  "russian_example_sentence": "Пусть тебе понадобится наша помощь.",
  "turkish_example_sentence": "Sen bizim yardımımıza ihtiyaç duyasın.",
  "turkish_example_sentence_with_blank": "Sen bizim yardımımıza ______."
}