{
  "verb_rank": 69,
  "verb_english": "to walk",
  "verb_russian": "ходить",
  "verb_infinitive": "yürümek",
  "turkish_verb": {
    "verb_full": "yürümeyeceğiz",
    "root": "yürü",
    "tense_affix": "yecek",
    "verb_tense": "gelecek_zaman",
    "personal_pronoun": "biz",
    "personal_affix": "iz",
    "polarity": "negative",
    "negative_affix": "me"
  },
  "english_example_sentence": "We will not walk in the park in this cold weather.",
  "russian_example_sentence": "Мы не будем гулять в парке в эту холодную погоду.",
  "turkish_example_sentence": "Biz bu soğuk havada parkta yürümeyeceğiz.",
  "turkish_example_sentence_with_blank": "Biz bu soğuk havada parkta ______."
}