{
  "verb_rank": 51,
  "verb_english": "include",
  "verb_russian": "включать",
  "verb_infinitive": "içermek",
  "turkish_verb": {
    "verb_full": "içerdiğimde",
    "root": "içer",
    "tense_affix": "diği",
    "verb_tense": "zaman_sıfatı",
    "personal_pronoun": "ben",
    "personal_affix": "mde",
    "polarity": "positive",
    "negative_affix": null
  },
  "english_example_sentence": "When I include fresh vegetables, the salad tastes better",
  "russian_example_sentence": "Когда я включаю свежие овощи, салат вкуснее",
  "turkish_example_sentence": "Ben taze sebzeleri içerdiğimde, salata daha lezzetli oluyor",
  "turkish_example_sentence_with_blank": "Ben taze sebzeleri ______, salata daha lezzetli oluyor"
}