{
  "verb_rank": 46,
  "verb_english": "sit",
  "verb_russian": "сидеть",
  "verb_infinitive": "oturmak",
  "turkish_verb": {
    "verb_full": "otursam",
    "root": "otur",
    "tense_affix": "sa",
    "verb_tense": "şart_kipi",
    "personal_pronoun": "ben",
    "personal_affix": "m",
    "polarity": "positive",
    "negative_affix": null
  },
  "english_example_sentence": "If I sit in this spacious park, it would be good",
  "russian_example_sentence": "Было бы хорошо, если бы я сидел в этом просторном парке",
  "turkish_example_sentence": "Ben bu geniş parkta otursam iyi olur",
  "turkish_example_sentence_with_blank": "Ben bu geniş parkta ______ iyi olur"
}