{
  "verb_rank": 15,
  "verb_english": "use",
  "verb_russian": "использовать",
  "verb_infinitive": "kullanmak",
  "turkish_verb": {
    "verb_full": "kullanmanız lazım",
    "root": "kullan",
    "tense_affix": "lazım",
    "verb_tense": "gereklilik_kipi",
    "personal_pronoun": "siz",
    "personal_affix": "nız",
    "polarity": "positive",
    "negative_affix": null
  },
  "english_example_sentence": "You all need to use the updated training manual",
  "russian_example_sentence": "Вам нужно использовать обновленное руководство обучения",
  "turkish_example_sentence": "Siz güncellenmiş eğitim kitapçığını kullanmanız lazım",
  "turkish_example_sentence_with_blank": "Siz güncellenmiş eğitim kitapçığını ______"
}