{
  "verb_rank": 88,
  "verb_english": "to remain",
  "verb_russian": "оставаться",
  "verb_infinitive": "kalmak",
  "turkish_verb": {
    "verb_full": "kalacaktın",
    "root": "kal",
    "tense_affix": "acaktı",
    "verb_tense": "geçmiş_gelecek_zaman",
    "personal_pronoun": "sen",
    "personal_affix": "n",
    "polarity": "positive",
    "negative_affix": null
  },
  "english_example_sentence": "You would have remained in the old house for a while longer.",
  "russian_example_sentence": "Ты бы остался в старом доме еще на некоторое время.",
  "turkish_example_sentence": "Sen, eski evde bir süre daha kalacaktın.",
  "turkish_example_sentence_with_blank": "Sen, eski evde bir süre daha ______."
}