{
  "verb_rank": 28,
  "verb_english": "mean",
  "verb_russian": "значить",
  "verb_infinitive": "demek",
  "turkish_verb": {
    "verb_full": "demeleri lazım",
    "root": "de",
    "tense_affix": "lazım",
    "verb_tense": "gereklilik_kipi",
    "personal_pronoun": "onlar",
    "personal_affix": "leri",
    "polarity": "positive",
    "negative_affix": null
  },
  "english_example_sentence": "They need to say goodbye to their old friends",
  "russian_example_sentence": "Они должны попрощаться со своими старыми друзьями",
  "turkish_example_sentence": "Onlar eski arkadaşlarına hoşça kalın demeleri lazım",
  "turkish_example_sentence_with_blank": "Onlar eski arkadaşlarına hoşça kalın ______"
}