{
  "verb_rank": 28,
  "verb_english": "mean",
  "verb_russian": "значить",
  "verb_infinitive": "demek",
  "turkish_verb": {
    "verb_full": "demezseniz",
    "root": "de",
    "tense_affix": "erse",
    "verb_tense": "şartlı_kipi",
    "personal_pronoun": "siz",
    "personal_affix": "niz",
    "polarity": "negative",
    "negative_affix": "mez"
  },
  "english_example_sentence": "If you do not speak, the situation will get worse.",
  "russian_example_sentence": "Если вы не будете говорить, ситуация ухудшится.",
  "turkish_example_sentence": "Konuşmazsanız, durum daha kötüleşir.",
  "turkish_example_sentence_with_blank": "Konuşmazsanız, durum daha kötüleşir."
}