{
  "verb_rank": 52,
  "verb_english": "continue",
  "verb_russian": "продолжать",
  "verb_infinitive": "devam etmek",
  "turkish_verb": {
    "verb_full": "devam etmediğimde",
    "root": "devam et",
    "tense_affix": "mediğ",
    "verb_tense": "zaman_sıfatı",
    "personal_pronoun": "ben",
    "personal_affix": "imde",
    "polarity": "negative",
    "negative_affix": "me"
  },
  "english_example_sentence": "When I don't continue my studies, I worry about exams",
  "russian_example_sentence": "Когда я не продолжаю учебу, я беспокоюсь об экзаменах",
  "turkish_example_sentence": "Ben ders çalışmasını devam etmediğimde, sınavlar hakkında endişeleniyorum",
  "turkish_example_sentence_with_blank": "Ben ders çalışmasını ______, sınavlar hakkında endişeleniyorum"
}