{
  "verb_rank": 36,
  "verb_english": "to play",
  "verb_russian": "играть",
  "verb_infinitive": "oynamak",
  "turkish_verb": {
    "verb_full": "oynamalıyım",
    "root": "oyna",
    "tense_affix": "malı",
    "verb_tense": "zorunluluk_kipi",
    "personal_pronoun": "ben",
    "personal_affix": "yım",
    "polarity": "positive",
    "negative_affix": null
  },
  "english_example_sentence": "I must play this important match well for my team.",
  "russian_example_sentence": "Я должен хорошо сыграть этот важный матч для своей команды.",
  "turkish_example_sentence": "Takımım için bu önemli maçı iyi oynamalıyım.",
  "turkish_example_sentence_with_blank": "Takımım için bu önemli maçı iyi ______."
}