{
  "verb_rank": 24,
  "verb_english": "feel",
  "verb_russian": "чувствовать",
  "verb_infinitive": "hissetmek",
  "turkish_verb": {
    "verb_full": "hissetmeyeceğim",
    "root": "hisset",
    "tense_affix": "yeceğ",
    "verb_tense": "gelecek_zaman",
    "personal_pronoun": "ben",
    "personal_affix": "im",
    "polarity": "negative",
    "negative_affix": "me"
  },
  "english_example_sentence": "I will not feel tired after the trip.",
  "russian_example_sentence": "Я не буду чувствовать усталость после поездки.",
  "turkish_example_sentence": "Yolculuktan sonra yorgunluk hissetmeyeceğim.",
  "turkish_example_sentence_with_blank": "Yolculuktan sonra yorgunluk ______."
}