{
  "verb_rank": 24,
  "verb_english": "feel",
  "verb_russian": "чувствовать",
  "verb_infinitive": "hissetmek",
  "turkish_verb": {
    "verb_full": "hissetmemişseniz",
    "root": "hisset",
    "tense_affix": "mişse",
    "verb_tense": "farzî_geçmiş_zaman",
    "personal_pronoun": "siz",
    "personal_affix": "niz",
    "polarity": "negative",
    "negative_affix": "me"
  },
  "english_example_sentence": "If you hadn't felt the biting wind.",
  "russian_example_sentence": "Если бы вы не почувствовали пронизывающий ветер.",
  "turkish_example_sentence": "Siz keskin rüzgarı hissetmemişseniz, kalın giyinmişsiniz demektir.",
  "turkish_example_sentence_with_blank": "Siz keskin rüzgarı ______, kalın giyinmişsiniz demektir."
}