{
  "verb_rank": 74,
  "verb_english": "to consider",
  "verb_russian": "рассматривать",
  "verb_infinitive": "düşünmek",
  "turkish_verb": {
    "verb_full": "düşünebilirsiniz",
    "root": "düşün",
    "tense_affix": "ebilir",
    "verb_tense": "imkan_kipi",
    "personal_pronoun": "siz",
    "personal_affix": "siniz",
    "polarity": "positive",
    "negative_affix": null
  },
  "english_example_sentence": "You can consider this difficult situation calmly.",
  "russian_example_sentence": "Вы можете спокойно обдумать эту сложную ситуацию.",
  "turkish_example_sentence": "Siz, bu zorlu durumu sakin bir şekilde düşünebilirsiniz.",
  "turkish_example_sentence_with_blank": "Siz, bu zorlu durumu sakin bir şekilde ______."
}