{
  "verb_rank": 58,
  "verb_english": "watch",
  "verb_russian": "смотреть",
  "verb_infinitive": "izlemek",
  "turkish_verb": {
    "verb_full": "izliyoruz",
    "root": "izle",
    "tense_affix": "iyor",
    "verb_tense": "şimdiki_zaman",
    "personal_pronoun": "biz",
    "personal_affix": "uz",
    "polarity": "positive",
    "negative_affix": null
  },
  "english_example_sentence": "We are watching the colorful nature documentary together",
  "russian_example_sentence": "Мы вместе смотрим красочный документальный фильм о природе",
  "turkish_example_sentence": "Biz birlikte renkli doğa belgeselini izliyoruz",
  "turkish_example_sentence_with_blank": "Biz birlikte renkli doğa belgeselini ______"
}