{
  "verb_rank": 58,
  "verb_english": "watch",
  "verb_russian": "смотреть",
  "verb_infinitive": "izlemek",
  "turkish_verb": {
    "verb_full": "izleyerek",
    "root": "izle",
    "tense_affix": "yerek",
    "verb_tense": "zarf_fiil",
    "personal_pronoun": null,
    "personal_affix": null,
    "polarity": "positive",
    "negative_affix": null
  },
  "english_example_sentence": "She learned by watching the detailed documentary carefully",
  "russian_example_sentence": "Она научилась, смотря подробный документальный фильм внимательно",
  "turkish_example_sentence": "Detaylı belgesel filmi izleyerek önemli bilgiler öğrendi",
  "turkish_example_sentence_with_blank": "Detaylı belgesel filmi ______ önemli bilgiler öğrendi"
}