{
  "verb_rank": 58,
  "verb_english": "watch",
  "verb_russian": "смотреть",
  "verb_infinitive": "izlemek",
  "turkish_verb": {
    "verb_full": "izlerse",
    "root": "izle",
    "tense_affix": "rse",
    "verb_tense": "şartlı_kipi",
    "personal_pronoun": "o",
    "personal_affix": null,
    "polarity": "positive",
    "negative_affix": null
  },
  "english_example_sentence": "If she watches the romantic comedy movie this weekend",
  "russian_example_sentence": "Если она смотрит романтическую комедию на выходных",
  "turkish_example_sentence": "Eğer o bu hafta sonu sevimli romantik komedyayı izlerse, çok gülecektir",
  "turkish_example_sentence_with_blank": "Eğer o bu hafta sonu sevimli romantik komedyayı ______, çok gülecektir"
}