{
  "verb_rank": 47,
  "verb_english": "stand",
  "verb_russian": "стоять",
  "verb_infinitive": "ayakta durmak",
  "turkish_verb": {
    "verb_full": "ayakta durabilir",
    "root": "ayakta dur",
    "tense_affix": "abilir",
    "verb_tense": "imkan_kipi",
    "personal_pronoun": "o",
    "personal_affix": "ir",
    "polarity": "positive",
    "negative_affix": null
  },
  "english_example_sentence": "He can stand in the long line.",
  "russian_example_sentence": "Он может простоять в длинной очереди.",
  "turkish_example_sentence": "O uzun sırada ayakta durabilir.",
  "turkish_example_sentence_with_blank": "O uzun sırada ______."
}