{
  "verb_rank": 39,
  "verb_english": "like",
  "verb_russian": "нравиться",
  "verb_infinitive": "sevmek",
  "turkish_verb": {
    "verb_full": "sevmesem",
    "root": "sev",
    "tense_affix": "mese",
    "verb_tense": "şart_kipi",
    "personal_pronoun": "ben",
    "personal_affix": "m",
    "polarity": "negative",
    "negative_affix": "me"
  },
  "english_example_sentence": "If I didn’t like this hat, I wouldn’t wear it",
  "russian_example_sentence": "Если бы мне не нравилась эта шляпа, я бы её не надел",
  "turkish_example_sentence": "Bu şapkayı sevmesem, onu takmazdım",
  "turkish_example_sentence_with_blank": "Bu şapkayı ______, onu takmazdım"
}