{
  "verb_rank": 7,
  "verb_english": "make",
  "verb_russian": "делать (создавать)",
  "verb_infinitive": "yapmak",
  "turkish_verb": {
    "verb_full": "yapmışsak",
    "root": "yap",
    "tense_affix": "mışsa",
    "verb_tense": "farzî_geçmiş_zaman",
    "personal_pronoun": "biz",
    "personal_affix": "k",
    "polarity": "positive",
    "negative_affix": null
  },
  "english_example_sentence": "If we had made that ambitious project successfully",
  "russian_example_sentence": "Если бы мы успешно сделали тот амбициозный проект",
  "turkish_example_sentence": "Biz o iddialı projeyi başarıyla yapmışsak, ödül kazanırdık",
  "turkish_example_sentence_with_blank": "Biz o iddialı projeyi başarıyla ______, ödül kazanırdık"
}