{
  "verb_rank": 63,
  "verb_english": "read",
  "verb_russian": "читать",
  "verb_infinitive": "okumak",
  "turkish_verb": {
    "verb_full": "okumaları lazım",
    "root": "oku",
    "tense_affix": "ma",
    "verb_tense": "gereklilik_kipi",
    "personal_pronoun": "onlar",
    "personal_affix": "ları",
    "polarity": "positive",
    "negative_affix": null
  },
  "english_example_sentence": "They need to read the books.",
  "russian_example_sentence": "Им нужно читать книги.",
  "turkish_example_sentence": "Öğrencilerin kitapları okumaları lazım.",
  "turkish_example_sentence_with_blank": "Öğrencilerin kitapları ______."
}