{
  "verb_rank": 62,
  "verb_english": "speak",
  "verb_russian": "говорить",
  "verb_infinitive": "konuşmak",
  "turkish_verb": {
    "verb_full": "konuşmanız lazım",
    "root": "konuş",
    "tense_affix": "lazım",
    "verb_tense": "gereklilik_kipi",
    "personal_pronoun": "siz",
    "personal_affix": "nız",
    "polarity": "positive",
    "negative_affix": null
  },
  "english_example_sentence": "You all need to speak clearly in the presentation",
  "russian_example_sentence": "Вам нужно четко говорить в презентации",
  "turkish_example_sentence": "Siz sunumda net ve anlaşılır konuşmanız lazım",
  "turkish_example_sentence_with_blank": "Siz sunumda net ve anlaşılır ______"
}