{
  "verb_rank": 17,
  "verb_english": "give",
  "verb_russian": "давать",
  "verb_infinitive": "vermek",
  "turkish_verb": {
    "verb_full": "vermediğinizde",
    "root": "ver",
    "tense_affix": "dik",
    "verb_tense": "zaman_sıfatı",
    "personal_pronoun": "siz",
    "personal_affix": "iniz",
    "polarity": "negative",
    "negative_affix": "me"
  },
  "english_example_sentence": "When you don't give clear explanations,",
  "russian_example_sentence": "Когда вы не даете четких объяснений,",
  "turkish_example_sentence": "Siz net açıklamalar vermediğinizde, insanlar anlamıyor.",
  "turkish_example_sentence_with_blank": "Siz net açıklamalar ______, insanlar anlamıyor."
}