{
  "verb_rank": 92,
  "verb_english": "sell",
  "verb_russian": "продавать",
  "verb_infinitive": "satmak",
  "turkish_verb": {
    "verb_full": "sattığınızda",
    "root": "sat",
    "tense_affix": "tık",
    "verb_tense": "zaman_sıfatı",
    "personal_pronoun": "siz",
    "personal_affix": "ınız",
    "polarity": "positive",
    "negative_affix": null
  },
  "english_example_sentence": "When you sell handmade jewelry",
  "russian_example_sentence": "Когда вы продаете ручные украшения",
  "turkish_example_sentence": "Siz el yapımı takıları sattığınızda",
  "turkish_example_sentence_with_blank": "Siz el yapımı takıları ______"
}