{
  "verb_rank": 92,
  "verb_english": "to sell",
  "verb_russian": "продавать",
  "verb_infinitive": "satmak",
  "turkish_verb": {
    "verb_full": "satmışsınız",
    "root": "sat",
    "tense_affix": "mış",
    "verb_tense": "farzî_geçmiş_zaman",
    "personal_pronoun": "siz",
    "personal_affix": "sınız",
    "polarity": "positive",
    "negative_affix": null
  },
  "english_example_sentence": "You must have sold your old house last week.",
  "russian_example_sentence": "Вы, должно быть, продали свой старый дом на прошлой неделе.",
  "turkish_example_sentence": "Siz, eski evinizi geçen hafta satmışsınız.",
  "turkish_example_sentence_with_blank": "Siz, eski evinizi geçen hafta ______."
}