{
  "verb_rank": 14,
  "verb_english": "look",
  "verb_russian": "смотреть",
  "verb_infinitive": "bakmak",
  "turkish_verb": {
    "verb_full": "bakacağız",
    "root": "bak",
    "tense_affix": "acak",
    "verb_tense": "şartlı_kipi",
    "personal_pronoun": "biz",
    "personal_affix": "ız",
    "polarity": "positive",
    "negative_affix": null
  },
  "english_example_sentence": "We will look at the beautiful painting.",
  "russian_example_sentence": "Мы посмотрим на прекрасную картину.",
  "turkish_example_sentence": "Biz güzel tabloya bakacağız.",
  "turkish_example_sentence_with_blank": "Biz güzel tabloya ______."
}