{
  "verb_rank": 14,
  "verb_english": "look",
  "verb_russian": "смотреть",
  "verb_infinitive": "bakmak",
  "turkish_verb": {
    "verb_full": "baktığım",
    "root": "bak",
    "tense_affix": "tığı",
    "verb_tense": "sıfat_fiil",
    "personal_pronoun": null,
    "personal_affix": "ım",
    "polarity": "positive",
    "negative_affix": null
  },
  "english_example_sentence": "I look at the beautiful garden every day.",
  "russian_example_sentence": "Я смотрю на красивый сад каждый день.",
  "turkish_example_sentence": "Her gün güzel bahçeye baktığım.",
  "turkish_example_sentence_with_blank": "Her gün güzel bahçeye ______."
}