{
  "verb_rank": 14,
  "verb_english": "look",
  "verb_russian": "смотреть",
  "verb_infinitive": "bakmak",
  "turkish_verb": {
    "verb_full": "bakın",
    "root": "bak",
    "tense_affix": "",
    "verb_tense": "emir_kipi",
    "personal_pronoun": "siz",
    "personal_affix": "ın",
    "polarity": "positive",
    "negative_affix": null
  },
  "english_example_sentence": "Please look at the beautiful flowers in the garden.",
  "russian_example_sentence": "Пожалуйста, посмотрите на красивые цветы в саду.",
  "turkish_example_sentence": "Bahçedeki güzel çiçeklere bakın.",
  "turkish_example_sentence_with_blank": "Bahçedeki güzel çiçeklere ______."
}