{
  "verb_rank": 77,
  "verb_english": "wait",
  "verb_russian": "ждать",
  "verb_infinitive": "beklemek",
  "turkish_verb": {
    "verb_full": "bekleseler",
    "root": "bekle",
    "tense_affix": "se",
    "verb_tense": "şartlı_kipi",
    "personal_pronoun": "onlar",
    "personal_affix": "ler",
    "polarity": "positive",
    "negative_affix": null
  },
  "english_example_sentence": "If the tired guests wait a little, their coffees will be ready.",
  "russian_example_sentence": "Если уставшие гости немного подождут, их кофе будет готов.",
  "turkish_example_sentence": "Eğer yorgun misafirler biraz bekleseler, kahveleri hazır olur.",
  "turkish_example_sentence_with_blank": "Eğer yorgun misafirler biraz ______, kahveleri hazır olur."
}