{
  "verb_rank": 60,
  "verb_english": "stop",
  "verb_russian": "останавливать",
  "verb_infinitive": "durmak",
  "turkish_verb": {
    "verb_full": "duruyor",
    "root": "dur",
    "tense_affix": "uyor",
    "verb_tense": "şimdiki_zaman",
    "personal_pronoun": "o",
    "personal_affix": null,
    "polarity": "positive",
    "negative_affix": null
  },
  "english_example_sentence": "He is stopping the old yellow bus",
  "russian_example_sentence": "Он останавливает старый жёлтый автобус",
  "turkish_example_sentence": "O eski sarı otobüsü duruyor",
  "turkish_example_sentence_with_blank": "O eski sarı otobüsü ______"
}