{
  "verb_rank": 90,
  "verb_english": "raise",
  "verb_russian": "поднимать",
  "verb_infinitive": "kaldırmak",
  "turkish_verb": {
    "verb_full": "kaldırsınlar",
    "root": "kaldır",
    "tense_affix": "",
    "verb_tense": "emir_kipi",
    "personal_pronoun": "onlar",
    "personal_affix": "sınlar",
    "polarity": "positive",
    "negative_affix": null
  },
  "english_example_sentence": "Let them raise the new steel beams carefully today",
  "russian_example_sentence": "Пусть они поднимают новые стальные балки осторожно сегодня",
  "turkish_example_sentence": "Bugün yeni çelik kirişleri dikkatle kaldırsınlar lütfen",
  "turkish_example_sentence_with_blank": "Bugün yeni çelik kirişleri dikkatle ______ lütfen"
}