{
  "verb_rank": 63,
  "verb_english": "read",
  "verb_russian": "читать",
  "verb_infinitive": "okumak",
  "turkish_verb": {
    "verb_full": "okuyor",
    "root": "oku",
    "tense_affix": "yor",
    "verb_tense": "şimdiki_zaman",
    "personal_pronoun": "o",
    "personal_affix": "",
    "polarity": "positive",
    "negative_affix": null
  },
  "english_example_sentence": "The little child is reading a book.",
  "russian_example_sentence": "Маленький ребенок читает книгу.",
  "turkish_example_sentence": "Küçük çocuk bir kitap okuyor.",
  "turkish_example_sentence_with_blank": "Küçük çocuk bir kitap ______."
}