{
  "verb_rank": 33,
  "verb_english": "help",
  "verb_russian": "помогать",
  "verb_infinitive": "yardım etmek",
  "turkish_verb": {
    "verb_full": "yardım etmememiz lazım",
    "root": "yardım et",
    "tense_affix": "me",
    "verb_tense": "gereklilik_kipi",
    "personal_pronoun": "biz",
    "personal_affix": "miz",
    "polarity": "negative",
    "negative_affix": "me"
  },
  "english_example_sentence": "We should not help with the dangerous mountain rescue",
  "russian_example_sentence": "Нам не нужно помогать с опасным горным спасением",
  "turkish_example_sentence": "Biz tehlikeli dağ kurtarma operasyonunda yardım etmememiz lazım",
  "turkish_example_sentence_with_blank": "Biz tehlikeli dağ kurtarma operasyonunda ______"
}