{
  "verb_rank": 33,
  "verb_english": "help",
  "verb_russian": "помогать",
  "verb_infinitive": "yardım etmek",
  "turkish_verb": {
    "verb_full": "yardım etseler",
    "root": "yardım et",
    "tense_affix": "se",
    "verb_tense": "şart_kipi",
    "personal_pronoun": "onlar",
    "personal_affix": "ler",
    "polarity": "positive",
    "negative_affix": null
  },
  "english_example_sentence": "If they help us, it will be great.",
  "russian_example_sentence": "Если они помогут нам, это будет здорово.",
  "turkish_example_sentence": "Onlar bize yardım etseler harika olur.",
  "turkish_example_sentence_with_blank": "Onlar bize ______ harika olur."
}