{
  "verb_rank": 26,
  "verb_english": "leave",
  "verb_russian": "покидать",
  "verb_infinitive": "ayrılmak",
  "turkish_verb": {
    "verb_full": "ayrılman lazım",
    "root": "ayrıl",
    "tense_affix": "ma",
    "verb_tense": "gereklilik_kipi",
    "personal_pronoun": "sen",
    "personal_affix": "n",
    "polarity": "positive",
    "negative_affix": null
  },
  "english_example_sentence": "You need to leave this dangerous neighborhood",
  "russian_example_sentence": "Тебе нужно уехать из этого опасного района",
  "turkish_example_sentence": "Sen tehlikeli mahallede ayrılman lazım",
  "turkish_example_sentence_with_blank": "Sen tehlikeli mahallede ______"
}