{
  "verb_rank": 116,
  "verb_english": "to serve (food)",
  "verb_russian": "подавать",
  "verb_infinitive": "servis yapmak",
  "turkish_verb": {
    "verb_full": "servis yapacağız",
    "root": "yap",
    "tense_affix": "acak",
    "verb_tense": "yaracağım",
    "personal_pronoun": "biz",
    "personal_affix": "ız",
    "polarity": "positive",
    "negative_affix": null
  },
  "english_example_sentence": "My friends and I will serve delicious meals to our special guests tomorrow.",
  "russian_example_sentence": "Мы с друзьями подадим вкусные блюда нашим особым гостям завтра.",
  "turkish_example_sentence": "Ben ve arkadaşlarım, yarın özel misafirlerimize lezzetli yemekler servis yapacağız.",
  "turkish_example_sentence_with_blank": "Ben ve arkadaşlarım, yarın özel misafirlerimize lezzetli yemekler ______."
}