{
  "verb_rank": 13,
  "verb_english": "want",
  "verb_russian": "хотеть",
  "verb_infinitive": "istemek",
  "turkish_verb": {
    "verb_full": "istediğin",
    "root": "iste",
    "tense_affix": "diğ",
    "verb_tense": "zaman_sıfatı",
    "personal_pronoun": "sen",
    "personal_affix": "in",
    "polarity": "positive",
    "negative_affix": null
  },
  "english_example_sentence": "The new book you wanted is on the table.",
  "russian_example_sentence": "Новая книга, которую ты хотел, лежит на столе.",
  "turkish_example_sentence": "Senin istediğin yeni kitap, masanın üzerinde duruyor.",
  "turkish_example_sentence_with_blank": "Senin ______ yeni kitap, masanın üzerinde duruyor."
}