{
  "verb_rank": 67,
  "verb_english": "grow",
  "verb_russian": "расти",
  "verb_infinitive": "büyümek",
  "turkish_verb": {
    "verb_full": "büyümüşseniz",
    "root": "büyü",
    "tense_affix": "müşse",
    "verb_tense": "farzî_geçmiş_zaman",
    "personal_pronoun": "siz",
    "personal_affix": "niz",
    "polarity": "positive",
    "negative_affix": null
  },
  "english_example_sentence": "If you had grown plants, they would flower now.",
  "russian_example_sentence": "Если бы вы посадили растения, они бы теперь цвели.",
  "turkish_example_sentence": "Eğer bitkiler büyütmüşseniz, şimdi çiçek açarlardı.",
  "turkish_example_sentence_with_blank": "Eğer bitkiler büyütmüşseniz, şimdi çiçek açarlardı."
}