{
  "verb_rank": 24,
  "verb_english": "feel",
  "verb_russian": "чувствовать",
  "verb_infinitive": "hissetmek",
  "turkish_verb": {
    "verb_full": "hissetmeyiz",
    "root": "hisset",
    "tense_affix": "",
    "verb_tense": "geniş_zaman",
    "personal_pronoun": "biz",
    "personal_affix": "yiz",
    "polarity": "negative",
    "negative_affix": "me"
  },
  "english_example_sentence": "We don't feel good in this cold weather.",
  "russian_example_sentence": "Мы не чувствуем себя хорошо в эту холодную погоду.",
  "turkish_example_sentence": "Biz bu soğuk havada kendimizi iyi hissetmeyiz.",
  "turkish_example_sentence_with_blank": "Biz bu soğuk havada kendimizi iyi ______."
}