{
  "verb_rank": 24,
  "verb_english": "feel",
  "verb_russian": "чувствовать",
  "verb_infinitive": "hissetmek",
  "turkish_verb": {
    "verb_full": "hissedeceksiniz",
    "root": "hisset",
    "tense_affix": "ecek",
    "verb_tense": "gelecek_zaman",
    "personal_pronoun": "siz",
    "personal_affix": "siniz",
    "polarity": "positive",
    "negative_affix": null
  },
  "english_example_sentence": "You will feel very happy in your new job.",
  "russian_example_sentence": "Вы будете чувствовать себя очень счастливыми на вашей новой работе.",
  "turkish_example_sentence": "Siz yeni işinizde çok mutlu hissedeceksiniz.",
  "turkish_example_sentence_with_blank": "Siz yeni işinizde çok mutlu ______."
}