{
  "verb_rank": 99,
  "verb_english": "to hope",
  "verb_russian": "надеяться",
  "verb_infinitive": "ummak",
  "turkish_verb": {
    "verb_full": "umdunuz",
    "root": "um",
    "tense_affix": "du",
    "verb_tense": "geçmiş_zaman",
    "personal_pronoun": "siz",
    "personal_affix": "nuz",
    "polarity": "positive",
    "negative_affix": null
  },
  "english_example_sentence": "You hoped for good results from this beautiful project.",
  "russian_example_sentence": "Вы надеялись на хорошие результаты от этого прекрасного проекта.",
  "turkish_example_sentence": "Siz, bu güzel projeden iyi sonuçlar umdunuz.",
  "turkish_example_sentence_with_blank": "Siz, bu güzel projeden iyi sonuçlar ______."
}