{
  "verb_rank": 1,
  "verb_english": "be",
  "verb_russian": "быть",
  "verb_infinitive": "olmak",
  "turkish_verb": {
    "verb_full": "olacağım",
    "root": "ol",
    "tense_affix": "acak",
    "verb_tense": "gelecek_zaman",
    "personal_pronoun": "o",
    "personal_affix": "ım",
    "polarity": "positive",
    "negative_affix": null
  },
  "english_example_sentence": "He will be happy next year.",
  "russian_example_sentence": "Он будет счастлив в следующем году.",
  "turkish_example_sentence": "Ali gelecek yıl mutlu olacağıma inanıyor.",
  "turkish_example_sentence_with_blank": "Ali gelecek yıl mutlu ______a inanıyor."
}