{
  "verb_rank": 1,
  "verb_english": "be",
  "verb_russian": "быть",
  "verb_infinitive": "olmak",
  "turkish_verb": {
    "verb_full": "olmazsın",
    "root": "ol",
    "tense_affix": "ur",
    "verb_tense": "geniş_zaman",
    "personal_pronoun": "sen",
    "personal_affix": "sun",
    "polarity": "negative",
    "negative_affix": "ma"
  },
  "english_example_sentence": "You are not usually impatient with children",
  "russian_example_sentence": "Ты обычно не нетерпелив с детьми",
  "turkish_example_sentence": "Sen çocuklarla sabırsız olmazsın",
  "turkish_example_sentence_with_blank": "Sen çocuklarla sabırsız ______"
}