{
  "verb_rank": 1,
  "verb_english": "be",
  "verb_russian": "быть",
  "verb_infinitive": "olmak",
  "turkish_verb": {
    "verb_full": "olursan",
    "root": "ol",
    "tense_affix": "ursa",
    "verb_tense": "şartlı_kipi",
    "personal_pronoun": "sen",
    "personal_affix": "n",
    "polarity": "positive",
    "negative_affix": null
  },
  "english_example_sentence": "If you are tired, you can rest.",
  "russian_example_sentence": "Если ты устал, можешь отдохнуть.",
  "turkish_example_sentence": "Eğer yorgun olursan dinlenebilirsin.",
  "turkish_example_sentence_with_blank": "Eğer yorgun ______ dinlenebilirsin."
}