{
  "verb_rank": 56,
  "verb_english": "lead",
  "verb_russian": "вести",
  "verb_infinitive": "öncülük etmek",
  "turkish_verb": {
    "verb_full": "öncülük edelim",
    "root": "öncülük et",
    "tense_affix": "e",
    "verb_tense": "istek_kipi",
    "personal_pronoun": "biz",
    "personal_affix": "lim",
    "polarity": "positive",
    "negative_affix": null
  },
  "english_example_sentence": "Let's lead in this important project.",
  "russian_example_sentence": "Давайте возглавим этот важный проект.",
  "turkish_example_sentence": "Biz bu önemli projede öncülük edelim.",
  "turkish_example_sentence_with_blank": "Biz bu önemli projede ______."
}