{
  "verb_rank": 4,
  "verb_english": "say",
  "verb_russian": "сказать",
  "verb_infinitive": "söylemek",
  "turkish_verb": {
    "verb_full": "söylemiş",
    "root": "söyle",
    "tense_affix": "miş",
    "verb_tense": "farzî_geçmiş_zaman",
    "personal_pronoun": "o",
    "personal_affix": "",
    "polarity": "positive",
    "negative_affix": null
  },
  "english_example_sentence": "My neighbor said that already.",
  "russian_example_sentence": "Мой сосед это уже сказал.",
  "turkish_example_sentence": "Komşum bunu çoktan söylemiş.",
  "turkish_example_sentence_with_blank": "Komşum bunu çoktan ______."
}