{
  "verb_rank": 10,
  "verb_english": "take",
  "verb_russian": "брать",
  "verb_infinitive": "almak",
  "turkish_verb": {
    "verb_full": "alacağız",
    "root": "al",
    "tense_affix": "acak",
    "verb_tense": "gelecek_zaman",
    "personal_pronoun": "biz",
    "personal_affix": "ız",
    "polarity": "positive",
    "negative_affix": null
  },
  "english_example_sentence": "We will take the comfortable chairs to the garden",
  "russian_example_sentence": "Мы возьмем удобные стулья в сад",
  "turkish_example_sentence": "Biz bahçeye rahat sandalyeleri alacağız",
  "turkish_example_sentence_with_blank": "Biz bahçeye rahat sandalyeleri ______"
}