{
  "verb_rank": 10,
  "verb_english": "take",
  "verb_russian": "брать",
  "verb_infinitive": "almak",
  "turkish_verb": {
    "verb_full": "almıyoruz",
    "root": "al",
    "tense_affix": "ıyor",
    "verb_tense": "şimdiki_zaman",
    "personal_pronoun": "biz",
    "personal_affix": "uz",
    "polarity": "negative",
    "negative_affix": "m"
  },
  "english_example_sentence": "We are not taking the heavy black suitcases on vacation",
  "russian_example_sentence": "Мы не берем тяжелые черные чемоданы в отпуск",
  "turkish_example_sentence": "Biz tatile ağır siyah bavulları almıyoruz",
  "turkish_example_sentence_with_blank": "Biz tatile ağır siyah bavulları ______"
}