{
  "verb_rank": 10,
  "verb_english": "take",
  "verb_russian": "брать",
  "verb_infinitive": "almak",
  "turkish_verb": {
    "verb_full": "alamazsınız",
    "root": "al",
    "tense_affix": "ama",
    "verb_tense": "imkan_kipi",
    "personal_pronoun": "siz",
    "personal_affix": "zsınız",
    "polarity": "negative",
    "negative_affix": "ama"
  },
  "english_example_sentence": "You cannot take the fragile glass vase to the moving truck",
  "russian_example_sentence": "Вы не можете взять хрупкую стеклянную вазу на грузовик",
  "turkish_example_sentence": "Siz kırılgan cam vazoyu taşıma kamyonuna alamazsınız",
  "turkish_example_sentence_with_blank": "Siz kırılgan cam vazoyu taşıma kamyonuna ______"
}