{
  "verb_rank": 103,
  "verb_english": "to receive",
  "verb_russian": "получать",
  "verb_infinitive": "almak",
  "turkish_verb": {
    "verb_full": "alacaklardı",
    "root": "al",
    "tense_affix": "acaktı",
    "verb_tense": "geçmiş_gelecek_zaman",
    "personal_pronoun": "onlar",
    "personal_affix": "lar",
    "polarity": "positive",
    "negative_affix": null
  },
  "english_example_sentence": "Old friends would receive a beautiful gift.",
  "russian_example_sentence": "Старые друзья получили бы красивый подарок.",
  "turkish_example_sentence": "Eski dostlar güzel bir hediye alacaklardı.",
  "turkish_example_sentence_with_blank": "Eski dostlar güzel bir hediye ______."
}