{
  "verb_rank": 18,
  "verb_english": "tell",
  "verb_russian": "рассказывать",
  "verb_infinitive": "anlatmak",
  "turkish_verb": {
    "verb_full": "anlatmayan",
    "root": "anlat",
    "tense_affix": "an",
    "verb_tense": "sıfat_fiil",
    "personal_pronoun": null,
    "personal_affix": null,
    "polarity": "negative",
    "negative_affix": "ma"
  },
  "english_example_sentence": "The child not telling the truth is shy.",
  "russian_example_sentence": "Ребенок, не говорящий правду, стесняется.",
  "turkish_example_sentence": "Doğruyu anlatmayan çocuk utangaç.",
  "turkish_example_sentence_with_blank": "Doğruyu ______ çocuk utangaç."
}