{
  "verb_rank": 83,
  "verb_english": "stay",
  "verb_russian": "оставаться",
  "verb_infinitive": "kalmak",
  "turkish_verb": {
    "verb_full": "kalabilirsiniz",
    "root": "kal",
    "tense_affix": "abil",
    "verb_tense": "imkan_kipi",
    "personal_pronoun": "siz",
    "personal_affix": "irsiniz",
    "polarity": "positive",
    "negative_affix": null
  },
  "english_example_sentence": "You can stay at the modern downtown apartment building",
  "russian_example_sentence": "Вы можете остаться в современном здании квартир в центре города",
  "turkish_example_sentence": "Siz modern şehir merkezi apartman binasında kalabilirsiniz",
  "turkish_example_sentence_with_blank": "Siz modern şehir merkezi apartman binasında ______"
}