{
  "verb_rank": 83,
  "verb_english": "to stay",
  "verb_russian": "оставаться",
  "verb_infinitive": "kalmak",
  "turkish_verb": {
    "verb_full": "kalsanız",
    "root": "kal",
    "tense_affix": "sa",
    "verb_tense": "şart_kipi",
    "personal_pronoun": "siz",
    "personal_affix": "nız",
    "polarity": "positive",
    "negative_affix": null
  },
  "english_example_sentence": "Dear guests, if you stay here, the meeting will be more productive.",
  "russian_example_sentence": "Дорогие гости, если вы останетесь здесь, встреча будет более продуктивной.",
  "turkish_example_sentence": "Değerli misafirlerimiz, burada kalsanız, toplantı daha verimli geçer.",
  "turkish_example_sentence_with_blank": "Değerli misafirlerimiz, burada ______, toplantı daha verimli geçer."
}