{
  "verb_rank": 19,
  "verb_english": "work",
  "verb_russian": "работать",
  "verb_infinitive": "çalışmak",
  "turkish_verb": {
    "verb_full": "çalışacak",
    "root": "çalış",
    "tense_affix": "acak",
    "verb_tense": "gelecek_zaman",
    "personal_pronoun": "o",
    "personal_affix": "ı",
    "polarity": "positive",
    "negative_affix": null
  },
  "english_example_sentence": "My friend will work at the new company.",
  "russian_example_sentence": "Мой друг будет работать в новой компании.",
  "turkish_example_sentence": "Arkadaşım yeni şirkette çalışacak.",
  "turkish_example_sentence_with_blank": "Arkadaşım yeni şirkette ______."
}