{
  "verb_rank": 12,
  "verb_english": "to come",
  "verb_russian": "приходить",
  "verb_infinitive": "gelmek",
  "turkish_verb": {
    "verb_full": "gelenler",
    "root": "gel",
    "tense_affix": "en",
    "verb_tense": "zaman_sıfatı",
    "personal_pronoun": "onlar",
    "personal_affix": "ler",
    "polarity": "positive",
    "negative_affix": null
  },
  "english_example_sentence": "The ones who came yesterday brought important news.",
  "russian_example_sentence": "Те, кто пришел вчера, принесли важные новости.",
  "turkish_example_sentence": "Dün gelenler, önemli haberler getirdi.",
  "turkish_example_sentence_with_blank": "Dün ______, önemli haberler getirdi."
}