{
  "verb_rank": 12,
  "verb_english": "come",
  "verb_russian": "приходить",
  "verb_infinitive": "gelmek",
  "turkish_verb": {
    "verb_full": "gelesin",
    "root": "gel",
    "tense_affix": "e",
    "verb_tense": "istek_kipi",
    "personal_pronoun": "sen",
    "personal_affix": "sin",
    "polarity": "positive",
    "negative_affix": null
  },
  "english_example_sentence": "I hope you also come to this important event on time.",
  "russian_example_sentence": "Надеюсь, ты тоже придешь на это важное событие вовремя.",
  "turkish_example_sentence": "Umarım sen de bu önemli etkinliğe zamanında gelesin.",
  "turkish_example_sentence_with_blank": "Umarım sen de bu önemli etkinliğe zamanında ______."
}