{
  "verb_rank": 105,
  "verb_english": "support",
  "verb_russian": "поддерживать",
  "verb_infinitive": "desteklemek",
  "turkish_verb": {
    "verb_full": "destekleyecekler",
    "root": "destekle",
    "tense_affix": "yecek",
    "verb_tense": "gelecek_zaman",
    "personal_pronoun": "onlar",
    "personal_affix": "ler",
    "polarity": "positive",
    "negative_affix": null
  },
  "english_example_sentence": "The young teachers at school will support this new student.",
  "russian_example_sentence": "Молодые учителя в школе поддержат этого нового ученика.",
  "turkish_example_sentence": "Okuldaki genç öğretmenler bu yeni öğrenciyi destekleyecekler.",
  "turkish_example_sentence_with_blank": "Okuldaki genç öğretmenler bu yeni öğrenciyi ______."
}