{
  "verb_rank": 34,
  "verb_english": "to show",
  "verb_russian": "показывать",
  "verb_infinitive": "göstermek",
  "turkish_verb": {
    "verb_full": "göstermezsin",
    "root": "göster",
    "tense_affix": "",
    "verb_tense": "geniş_zaman",
    "personal_pronoun": "sen",
    "personal_affix": "zsin",
    "polarity": "negative",
    "negative_affix": "me"
  },
  "english_example_sentence": "You don't show the correct way to anyone.",
  "russian_example_sentence": "Ты никому не показываешь правильный путь.",
  "turkish_example_sentence": "Sen doğru yolu kimseye göstermezsin.",
  "turkish_example_sentence_with_blank": "Sen doğru yolu kimseye ______."
}