{
  "verb_rank": 6,
  "verb_english": "to get (receive)",
  "verb_russian": "получать",
  "verb_infinitive": "almak",
  "turkish_verb": {
    "verb_full": "almayacağız",
    "root": "al",
    "tense_affix": "yacak",
    "verb_tense": "gelecek_zaman",
    "personal_pronoun": "biz",
    "personal_affix": "ız",
    "polarity": "negative",
    "negative_affix": "ma"
  },
  "english_example_sentence": "We will not get a new car this year.",
  "russian_example_sentence": "Мы не получим новую машину в этом году.",
  "turkish_example_sentence": "Biz bu yıl yeni bir araba almayacağız.",
  "turkish_example_sentence_with_blank": "Biz bu yıl yeni bir araba ______."
}