{
  "verb_rank": 6,
  "verb_english": "get",
  "verb_russian": "получать",
  "verb_infinitive": "almak",
  "turkish_verb": {
    "verb_full": "almadıklarında",
    "root": "al",
    "tense_affix": "dığ",
    "verb_tense": "zaman_sıfatı",
    "personal_pronoun": "onlar",
    "personal_affix": "larında",
    "polarity": "negative",
    "negative_affix": "ma"
  },
  "english_example_sentence": "When they don't receive the payment confirmation, they send a reminder",
  "russian_example_sentence": "Когда они не получают подтверждение платежа, они отправляют напоминание",
  "turkish_example_sentence": "Onlar ödeme onayını almadıklarında, hatırlatma gönderiyorlar",
  "turkish_example_sentence_with_blank": "Onlar ödeme onayını ______, hatırlatma gönderiyorlar"
}