{
  "verb_rank": 6,
  "verb_english": "get",
  "verb_russian": "получать",
  "verb_infinitive": "almak",
  "turkish_verb": {
    "verb_full": "alırsanız",
    "root": "al",
    "tense_affix": "ırsanız",
    "verb_tense": "şartlı_kipi",
    "personal_pronoun": "siz",
    "personal_affix": "nız",
    "polarity": "positive",
    "negative_affix": null
  },
  "english_example_sentence": "If you get the information,",
  "russian_example_sentence": "Если вы получите информацию,",
  "turkish_example_sentence": "Siz bilgiyi alırsanız, bana hemen haber verin.",
  "turkish_example_sentence_with_blank": "Siz bilgiyi ______, bana hemen haber verin."
}