{
  "verb_rank": 108,
  "verb_english": "to eat",
  "verb_russian": "есть",
  "verb_infinitive": "yemek",
  "turkish_verb": {
    "verb_full": "yemiyoruz",
    "root": "ye",
    "tense_affix": "yor",
    "verb_tense": "şimdiki_zaman",
    "personal_pronoun": "biz",
    "personal_affix": "uz",
    "polarity": "negative",
    "negative_affix": "mi"
  },
  "english_example_sentence": "We are not eating delicious food tonight.",
  "russian_example_sentence": "Мы не едим вкусную еду сегодня вечером.",
  "turkish_example_sentence": "Biz bu akşam lezzetli yemek yemiyoruz.",
  "turkish_example_sentence_with_blank": "Biz bu akşam lezzetli yemek ______."
}