{
  "verb_rank": 97,
  "verb_english": "return",
  "verb_russian": "возвращаться",
  "verb_infinitive": "dönmek",
  "turkish_verb": {
    "verb_full": "dönmemelisin",
    "root": "dön",
    "tense_affix": "meli",
    "verb_tense": "zorunluluk_kipi",
    "personal_pronoun": "sen",
    "personal_affix": "sin",
    "polarity": "negative",
    "negative_affix": "me"
  },
  "english_example_sentence": "You must not return to the same mistake again.",
  "russian_example_sentence": "Ты не должен снова совершить ту же ошибку.",
  "turkish_example_sentence": "Sen aynı hataya bir daha dönmemelisin.",
  "turkish_example_sentence_with_blank": "Sen aynı hataya bir daha ______."
}