{
  "verb_rank": 53,
  "verb_english": "to set (put, place)",
  "verb_russian": "ставить",
  "verb_infinitive": "koymak",
  "turkish_verb": {
    "verb_full": "koymayacaklar",
    "root": "koy",
    "tense_affix": "yacak",
    "verb_tense": "gelecek_zaman",
    "personal_pronoun": "onlar",
    "personal_affix": "lar",
    "polarity": "negative",
    "negative_affix": "ma"
  },
  "english_example_sentence": "The small children will not put their toys on the table.",
  "russian_example_sentence": "Маленькие дети не положат свои игрушки на стол.",
  "turkish_example_sentence": "Küçük çocuklar oyuncaklarını masaya koymayacaklar.",
  "turkish_example_sentence_with_blank": "Küçük çocuklar oyuncaklarını masaya ______."
}