{
  "verb_rank": 113,
  "verb_english": "to touch",
  "verb_russian": "трогать",
  "verb_infinitive": "dokunmak",
  "turkish_verb": {
    "verb_full": "dokunmuş",
    "root": "dokun",
    "tense_affix": "muş",
    "verb_tense": "farzî_geçmiş_zaman",
    "personal_pronoun": "o",
    "personal_affix": "",
    "polarity": "positive",
    "negative_affix": null
  },
  "english_example_sentence": "The small child must have touched the hot stove.",
  "russian_example_sentence": "Маленький ребенок, должно быть, прикоснулся к горячей плите.",
  "turkish_example_sentence": "Küçük çocuk sıcak sobaya dokunmuş.",
  "turkish_example_sentence_with_blank": "Küçük çocuk sıcak sobaya ______."
}