{
  "verb_rank": 22,
  "verb_english": "ask",
  "verb_russian": "спрашивать",
  "verb_infinitive": "sormak",
  "turkish_verb": {
    "verb_full": "soracaksınız",
    "root": "sor",
    "tense_affix": "acak",
    "verb_tense": "gelecek_zaman",
    "personal_pronoun": "siz",
    "personal_affix": "sınız",
    "polarity": "positive",
    "negative_affix": null
  },
  "english_example_sentence": "You will ask the talented musician about the beautiful composition",
  "russian_example_sentence": "Вы спросите талантливого музыканта о красивой композиции",
  "turkish_example_sentence": "Siz yetenekli müzisyene güzel bestesi hakkında soracaksınız",
  "turkish_example_sentence_with_blank": "Siz yetenekli müzisyene güzel bestesi hakkında ______"
}