{
  "verb_rank": 100,
  "verb_english": "develop",
  "verb_russian": "развивать",
  "verb_infinitive": "geliştirmek",
  "turkish_verb": {
    "verb_full": "geliştirmeliyiz",
    "root": "geliştir",
    "tense_affix": "meli",
    "verb_tense": "zorunluluk_kipi",
    "personal_pronoun": "biz",
    "personal_affix": "yiz",
    "polarity": "positive",
    "negative_affix": null
  },
  "english_example_sentence": "We must develop new and effective strategies for our company.",
  "russian_example_sentence": "Для нашей компании мы должны разработать новые и эффективные стратегии.",
  "turkish_example_sentence": "Şirketimiz için yeni ve etkili stratejiler geliştirmeliyiz.",
  "turkish_example_sentence_with_blank": "Şirketimiz için yeni ve etkili stratejiler ______."
}