{
  "verb_rank": 21,
  "verb_english": "try",
  "verb_russian": "пытаться",
  "verb_infinitive": "denemek",
  "turkish_verb": {
    "verb_full": "denemememeları lazım",
    "root": "dene",
    "tense_affix": "lazım",
    "verb_tense": "gereklilik_kipi",
    "personal_pronoun": "onlar",
    "personal_affix": "ları",
    "polarity": "negative",
    "negative_affix": "me"
  },
  "english_example_sentence": "They should not try those spicy hot pepper dishes",
  "russian_example_sentence": "Им не нужно пробовать эти острые горячие блюда с перцем",
  "turkish_example_sentence": "Onlar o acı sıcak biber yemeklerini denemememeları lazım",
  "turkish_example_sentence_with_blank": "Onlar o acı sıcak biber yemeklerini ______"
}