{
  "verb_rank": 92,
  "verb_english": "sell",
  "verb_russian": "продавать",
  "verb_infinitive": "satmak",
  "turkish_verb": {
    "verb_full": "satmalı",
    "root": "sat",
    "tense_affix": "malı",
    "verb_tense": "gereklilik_kipi",
    "personal_pronoun": "o",
    "personal_affix": "",
    "polarity": "positive",
    "negative_affix": null
  },
  "english_example_sentence": "My mother must sell her old car.",
  "russian_example_sentence": "Моя мама должна продать свою старую машину.",
  "turkish_example_sentence": "Annem eski arabasını satmalı.",
  "turkish_example_sentence_with_blank": "Annem eski arabasını ______."
}