{
  "verb_rank": 38,
  "verb_english": "move",
  "verb_russian": "двигаться",
  "verb_infinitive": "hareket etmek",
  "turkish_verb": {
    "verb_full": "hareket edecek",
    "root": "hareket et",
    "tense_affix": "ecek",
    "verb_tense": "şart_kipi",
    "personal_pronoun": "o",
    "personal_affix": "cek",
    "polarity": "positive",
    "negative_affix": null
  },
  "english_example_sentence": "The cat will move quickly.",
  "russian_example_sentence": "Кошка быстро двинется.",
  "turkish_example_sentence": "Kedi hızlı bir şekilde hareket edecek.",
  "turkish_example_sentence_with_blank": "Kedi hızlı bir şekilde ______."
}