{
  "verb_rank": 37,
  "verb_english": "run",
  "verb_russian": "бегать",
  "verb_infinitive": "koşmak",
  "turkish_verb": {
    "verb_full": "koşmayacaksınız",
    "root": "koş",
    "tense_affix": "acak",
    "verb_tense": "gelecek_zaman",
    "personal_pronoun": "siz",
    "personal_affix": "sınız",
    "polarity": "negative",
    "negative_affix": "ma"
  },
  "english_example_sentence": "You will not run on the slippery icy road",
  "russian_example_sentence": "Вы не будете бегать по скользкой ледяной дороге",
  "turkish_example_sentence": "Siz kaygan buzlu yolda tehlikeli koşmayacaksınız",
  "turkish_example_sentence_with_blank": "Siz kaygan buzlu yolda tehlikeli ______"
}