{
  "verb_rank": 255,
  "verb_english": "lead",
  "verb_russian": "вести",
  "verb_infinitive": "liderlik etmek",
  "turkish_verb": {
    "verb_full": "liderlik etmişsem",
    "root": "et",
    "tense_affix": "mişse",
    "verb_tense": "farzî_geçmiş_zaman",
    "personal_pronoun": "ben",
    "personal_affix": "m",
    "polarity": "positive",
    "negative_affix": null
  },
  "english_example_sentence": "If I had led the successful project yesterday",
  "russian_example_sentence": "Если бы я руководил успешным проектом вчера",
  "turkish_example_sentence": "Ben dün başarılı projeyi liderlik etmişsem, takım çok mutlu olurdu",
  "turkish_example_sentence_with_blank": "Ben dün başarılı projeyi ______, takım çok mutlu olurdu"
}