{
  "verb_rank": 38,
  "verb_english": "move",
  "verb_russian": "двигаться",
  "verb_infinitive": "hareket etmek",
  "turkish_verb": {
    "verb_full": "hareket etmen lazım değil",
    "root": "hareket et",
    "tense_affix": "lazım",
    "verb_tense": "gereklilik_kipi",
    "personal_pronoun": "sen",
    "personal_affix": "n",
    "polarity": "negative",
    "negative_affix": "değil"
  },
  "english_example_sentence": "You do not need to move during this peaceful meditation",
  "russian_example_sentence": "Тебе не нужно двигаться во время этой спокойной медитации",
  "turkish_example_sentence": "Sen sakin meditasyon sırasında hiç hareket etmen lazım değil",
  "turkish_example_sentence_with_blank": "Sen sakin meditasyon sırasında hiç ______"
}