{
  "verb_rank": 68,
  "verb_english": "to open",
  "verb_russian": "открывать",
  "verb_infinitive": "açmak",
  "turkish_verb": {
    "verb_full": "açabilir",
    "root": "aç",
    "tense_affix": "abilir",
    "verb_tense": "imkan_kipi",
    "personal_pronoun": "o",
    "personal_affix": "",
    "polarity": "positive",
    "negative_affix": null
  },
  "english_example_sentence": "The small child can open the new box.",
  "russian_example_sentence": "Маленький ребёнок может открыть новую коробку.",
  "turkish_example_sentence": "Küçük çocuk yeni kutuyu açabilir.",
  "turkish_example_sentence_with_blank": "Küçük çocuk yeni kutuyu ______."
}