{
  "verb_rank": 41,
  "verb_english": "believe",
  "verb_russian": "верить",
  "verb_infinitive": "inanmak",
  "turkish_verb": {
    "verb_full": "inandı",
    "root": "inan",
    "tense_affix": "dı",
    "verb_tense": "geçmiş_zaman",
    "personal_pronoun": "o",
    "personal_affix": null,
    "polarity": "positive",
    "negative_affix": null
  },
  "english_example_sentence": "She believed the mysterious promise easily",
  "russian_example_sentence": "Она верила таинственному обещанию легко",
  "turkish_example_sentence": "O gizemli sözü kolayca inandı",
  "turkish_example_sentence_with_blank": "O gizemli sözü kolayca ______"
}