{
  "verb_rank": 41,
  "verb_english": "believe",
  "verb_russian": "верить",
  "verb_infinitive": "inanmak",
  "turkish_verb": {
    "verb_full": "inanır",
    "root": "inan",
    "tense_affix": "ır",
    "verb_tense": "geniş_zaman",
    "personal_pronoun": "o",
    "personal_affix": null,
    "polarity": "positive",
    "negative_affix": null
  },
  "english_example_sentence": "He believes in hard work and dedication",
  "russian_example_sentence": "Он верит в упорный труд и преданность",
  "turkish_example_sentence": "O sıkı çalışmaya ve sadakate inanır",
  "turkish_example_sentence_with_blank": "O sıkı çalışmaya ve sadakate ______"
}