{
  "verb_rank": 3,
  "verb_english": "do",
  "verb_russian": "делать",
  "verb_infinitive": "yapmak",
  "turkish_verb": {
    "verb_full": "yapamaz",
    "root": "yap",
    "tense_affix": "abil",
    "verb_tense": "imkan_kipi",
    "personal_pronoun": "o",
    "personal_affix": "ir",
    "polarity": "negative",
    "negative_affix": "ama"
  },
  "english_example_sentence": "He cannot do the fast running exercise",
  "russian_example_sentence": "Он не может делать быстрое беговое упражнение",
  "turkish_example_sentence": "O hızlı koşu egzersizini yapamaz",
  "turkish_example_sentence_with_blank": "O hızlı koşu egzersizini ______"
}